testmoduletrolol/__init__.py
testmoduletrolol/add.py
testmoduletrolol/divide.py
testmoduletrolol/multiply.py
testmoduletrolol/subtract.py
testmoduletrolol-0.0.1.dist-info/METADATA
testmoduletrolol-0.0.1.dist-info/WHEEL
testmoduletrolol-0.0.1.dist-info/top_level.txt
testmoduletrolol-0.0.1.dist-info/RECORD
