Metadata-Version: 2.1
Name: testmoduletrolol
Version: 0.0.1
Summary: Sort of just a test, there's not much point to this.
Home-page: UNKNOWN
Author: xavvvv
Author-email: email@email.com
License: UNKNOWN
Keywords: python,first package
Platform: UNKNOWN
Classifier: Development Status :: 3 - Alpha
Classifier: Intended Audience :: Education
Classifier: Programming Language :: Python :: 2
Classifier: Programming Language :: Python :: 3
Classifier: Operating System :: MacOS :: MacOS X
Classifier: Operating System :: Microsoft :: Windows
